[
    {
        "id": "26914ae9-f9bc-424b-80e2-9f0339a18f10",
        "nombre": "Gorra clásicaa",
        "precio": 199,
        "imagen": "./src/assets/img/prueba01.png",
        "descripcion": "Gorra clásica de algodón con ajuste trasero.",
        "categoria": {
            "id": "planas",
            "nombre": "Planas"
        },
        "clase": "coders"
    },
    {
        "id": "f737e16e-aad3-4920-bb86-8e62ee63445e",
        "nombre": "Gorra deportiva",
        "precio": 299,
        "imagen": "./src/assets/img/gorra-deportiva.png",
        "descripcion": "Gorra ligera y transpirable, ideal para actividades deportivas.",
        "categoria": {
            "id": "viceras",
            "nombre": "Viceras"
        },
        "clase": "coders"
    },
    {
        "id": "76bf3ca6-290a-4601-a1cc-11ee90838d1d",
        "nombre": "Gorra snapback",
        "precio": 299,
        "imagen": "./src/assets/img/gorra-snapblack.png",
        "descripcion": "Gorra snapback ajustable con visera plana y diseño moderno.",
        "categoria": {
            "id": "planas",
            "nombre": "Planas2"
        },
        "clase": "coders"
    },
    {
        "id": "5c1576be-8199-4c21-9b42-0c40cea63b15",
        "nombre": "Gorra de camionero",
        "precio": 250,
        "imagen": "./src/assets/img/gorra-camionero.png",
        "descripcion": "Gorra de camionero con malla trasera y logotipo bordado.",
        "categoria" : {
            "id": "planas",
            "nombre": "Planas3"
        },
        "clase": "coders"
    },
    {
        "id": "3f951fc0-1a75-46e3-b699-d20144df237d",
        "nombre": "Gorra de lana",
        "precio": 399,
        "imagen": "./src/assets/img/gorra-lana.png",
        "descripcion": "Gorra de lana para mantener el calor en climas fríos.",
        "categoria": {
            "id": "gorros",
            "nombre": "Gorros"
        },
        "clase": "coders"
    },
    {
        "id": "6d5f6b5f-687f-47fb-a4d6-6a726b52d5bd",
        "nombre": "Gorra de béisbol",
        "precio": 199,
        "imagen": "./src/assets/img/gorra-beisbol.png",
        "descripcion": "Gorra de béisbol clásica con visera curva y ajuste trasero.",
        "categoria": {
            "id": "viceras",
            "nombre": "Viceras2"
        },
        "clase": "coders"
    },
    {
        "id": "aab0e74e-a49a-4e41-af49-5ed34f776dfa",
        "nombre": "Gorra de pescador",
        "precio": 299,
        "imagen": "./src/assets/img/gorra-pescador.png",
        "descripcion": "Gorra estilo pescador con ala ancha y cordón ajustable.",
        "categoria": {
            "id": "camufladas",
            "nombre": "Camufladas"
        },
        "clase": "coders"
    }
    
]